pip_shims/__init__.py
pip_shims/compat.py
pip_shims/environment.py
pip_shims/models.py
pip_shims/shims.py
pip_shims/utils.py
pip_shims-0.7.3.dist-info/LICENSE
pip_shims-0.7.3.dist-info/METADATA
pip_shims-0.7.3.dist-info/WHEEL
pip_shims-0.7.3.dist-info/top_level.txt
pip_shims-0.7.3.dist-info/zip-safe
pip_shims-0.7.3.dist-info/RECORD
