Metadata-Version: 2.1
Name: pip-shims
Version: 0.7.3
Summary: Compatibility shims for pip versions 8 thru current.
Home-page: https://github.com/sarugaku/pip-shims
Author: Dan Ryan
Author-email: dan@danryan.co
Maintainer: Frost Ming
Maintainer-email: mianghong@gmail.com
License: ISC License
Keywords: pip,compatibility,shims,api,pip-shims,pipenv,pip-compat
Classifier: Development Status :: 5 - Production/Stable
Classifier: License :: OSI Approved :: ISC License (ISCL)
Classifier: Operating System :: OS Independent
Classifier: Programming Language :: Python :: 2
Classifier: Programming Language :: Python :: 2.7
Classifier: Programming Language :: Python :: 3
Classifier: Programming Language :: Python :: 3.5
Classifier: Programming Language :: Python :: 3.6
Classifier: Programming Language :: Python :: 3.7
Classifier: Programming Language :: Python :: 3.8
Classifier: Topic :: Software Development :: Build Tools
Classifier: Topic :: Software Development :: Libraries :: Python Modules
Classifier: Topic :: Utilities
Requires-Python: >=3.6
Provides-Extra: tests
Provides-Extra: docs
Provides-Extra: dev
License-File: LICENSE
